{
    "来一杯": [
        "你在《Li BEng》酒吧的吧台坐下，点了一杯今日特饮。\n{今日特饮}。"
    ],
    "今日特饮": [
        "{普通特饮}",
        "{普通特饮}",
        "{普通特饮}",
        "{普通特饮}",
        "{特别特饮}"
    ],
    "普通特饮": [
        "调酒师给你上了一杯{特饮颜色}的{特饮温度}{特饮种类}，你拿起来喝一口，感觉味道{特饮口感}"
    ],
    "特别特饮": [
        "老板娘亲自给你上了一杯饮料，你拿起来准备喝一口，{特殊事件}"
    ],
    "特饮温度": [
        "冰",
        "冰",
        "冰",
        "热",
        "常温"
    ],
    "特饮颜色": [
        "黄色",
        "蓝色",
        "绿色",
        "青色",
        "紫色",
        "橙色",
        "黑色",
        "白色",
        "半透明",
        "深红色",
        "粉红色",
        "红黑色",
        "琥珀色",
        "蓝黄色",
        "蓝绿色",
        "五颜六色"
    ],
    "特饮种类": [
        "碳酸饮料",
        "调制乳饮",
        "气泡水",
        "蔬菜汁",
        "鸡尾酒",
        "水果茶",
        "果汁",
        "可可",
        "奶茶"
    ],
    "特饮口感": [
        "还不错",
        "有点酸",
        "有点甜",
        "有点苦",
        "有点涩",
        "有点淡"
    ],
    "特殊事件": [
        "杯子里面突然探出来了一只{猫猫}猫猫",
        "杯子里面突然探出来了一只{猫猫}猫猫",
        "杯子里面突然探出来了一只{猫猫}猫猫，{猫动作}",
        "杯子里面突然探出来了一只有着一双{猫瞳色1}眼睛的{猫猫}猫猫",
        "杯子里面突然探出来了一只有着一双{猫瞳色2}眼睛的{猫猫}猫猫",
        "杯子里面突然探出来了一只有着一双{猫瞳色1}眼睛的{猫猫}猫猫，{猫动作}",
        "杯子里面突然探出来了一只有着一双{猫瞳色2}眼睛的{猫猫}猫猫，{猫动作}",
        "杯子里面突然探出来了一只有着一边{猫瞳色1}一边{猫瞳色2}异色瞳的{猫猫}猫猫，{猫动作}"
    ],
    "猫瞳色1": [
        "天蓝色",
        "碧绿色",
        "琥珀色",
        "浓褐色",
        "淡褐色",
        "粉红色",
        "血红色",
        "鹅黄色",
        "红色",
        "金色",
        "黑色",
        "白色",
        "绿色",
        "灰色",
        "蓝色",
        "紫色"
    ],
    "猫瞳色2": [
        "墨色",
        "深红色",
        "蓝紫色",
        "石榴红",
        "淡蓝色",
        "浅灰色",
        "灰绿色",
        "宝石蓝",
        "紫钢色",
        "灰蓝色",
        "灰黑色"
    ],
    "猫猫": [
        "黑白相间的奶牛",
        "白手套的黑色",
        "粉爪爪的白色",
        "蓝灰色的绒绒",
        "粉红色的短毛",
        "淡紫色的波斯",
        "洁白的波斯",
        "绿色的短毛",
        "灰白相间的",
        "浑身纯黑的",
        "浑身洁白的",
        "淡黄色的",
        "亚麻色的",
        "银灰渐层",
        "灰色的",
        "长毛橘",
        "金渐层",
        "银渐层",
        "拿破仑",
        "狸花",
        "布偶"
    ],
    "猫动作": [
        "摇了摇尾巴",
        "与你四目相对",
        "抖了抖小耳朵",
        "对着你喵了一声",
        "举起小爪爪在你面前晃了晃",
        "不小心啄了你的{人部位}一下"
    ],
    "人部位": [
        "手背",
        "嘴唇",
        "脸蛋",
        "鼻子",
        "额头"
    ]
}
